{
    "shoes": [
        {
            "name": "Chicken Shoes",
            "price": 1000,
            "featured": true,
            "rating": 5,
            "createdAt": "2021-8-11",
            "company": "Wacky N Tacky",
            "image": "chicken.jfif"
        },
        {
            "name": "Banana Shoes",
            "price": 134,
            "featured": false,
            "rating": 4.7,
            "createdAt": "2021-7-6",
            "company": "Wacky N Tacky",
            "image": "bananaShoes.jfif"
        },
        {
            "name": "Brown... just Brown",
            "price": 89,
            "featured": true,
            "rating": 4.3,
            "createdAt": "2021-1-14",
            "company": "Plain Ol Corp.",
            "image": "brown.jfif"
        },
        {
            "name": "Even More Brown",
            "price": 160,
            "featured": false,
            "rating": 4.7,
            "createdAt": "2021-5-23",
            "company": "Plain Ol Corp.",
            "image": "moreBrown.jfif"
        },
        {
            "name": "Feet",
            "price": 200,
            "featured": false,
            "rating": 3,
            "createdAt": "2021-5-8",
            "company": "All Nature Al",
            "image": "feet.jpg"
        },
        {
            "name": "Grass",
            "price": 180,
            "featured": true,
            "rating": 5,
            "createdAt": "2021-8-17",
            "company": "Nike",
            "image": "grass.jpeg"
        },
        {
            "name": "Computer Shoes",
            "price": 1200,
            "featured": false,
            "rating": 2,
            "createdAt": "2021-2-21",
            "company": "Electrono's",
            "image": "computer.jpg"
        },
        {
            "name": "Bread Shoes",
            "price": 180,
            "featured": false,
            "rating": 4.5,
            "createdAt": "2021-2-2",
            "company": "Foot Cuisine",
            "image": "bread.jpg"
        },
        {
            "name": "Clown Shoes",
            "price": 213,
            "featured": true,
            "rating": 4.5,
            "createdAt": "2021-3-4",
            "company": "Wacky N Tacky",
            "image": "clown.jfif"
        },
        {
            "name": "Motor Shoes",
            "price": 500,
            "featured": false,
            "rating": 4.9,
            "createdAt": "2021-7-18",
            "company": "Electrono's",
            "image": "motor.jpg"
        },
        {
            "name": "Fish Shoes",
            "price": 999,
            "featured": true,
            "rating": 3.5,
            "createdAt": "2019-2-17",
            "company": "All Nature Al",
            "image": "fish.jfif"
        },
        {
            "name": "Bubble wrap",
            "price": 673,
            "featured": true,
            "rating": 4.3,
            "createdAt": "2020-5-30",
            "company": "Wacky N Tacky",
            "image": "bubble_wrap.jpg"
        },
        {
            "name": "Elmo",
            "price": 577,
            "featured": false,
            "rating": 3.2,
            "createdAt": "2021-3-1",
            "company": "Plain Ol Corp.",
            "image": "elmo.jfif"
        },
        {
            "name": "Leprechaun",
            "price": 190,
            "featured": true,
            "rating": 4.8,
            "createdAt": "2021-3-16",
            "company": "Wacky N Tacky",
            "image": "leprechaun.jfif"
        },
        {
            "name": "Jean Shoes",
            "price": 67,
            "featured": false,
            "rating": 4.5,
            "createdAt": "2019-9-20",
            "company": "Plain Ol Corp.",
            "image": "jeans.jpg"
        },
        {
            "name": "Teeth Shoes",
            "price": 230,
            "featured": false,
            "rating": 5,
            "createdAt": "2021-9-8",
            "company": "All Nature Al",
            "image": "teeth.jfif"
        },
        {
            "name": "Copper Shoes",
            "price": 400,
            "featured": true,
            "rating": 4.5,
            "createdAt": "2020-7-13",
            "company": "Electrono's",
            "image": "copper.jpg"
        },
        {
            "name": "Circuit Board Shoes",
            "price": 360,
            "featured": false,
            "rating": 4.8,
            "createdAt": "2020-4-27",
            "company": "Electrono's",
            "image": "circuit.jfif"
        },
        {
            "name": "Gum Shoe",
            "price": 110,
            "featured": true,
            "rating": 4.9,
            "createdAt": "2021-7-18",
            "company": "Wacky N Tacky",
            "image": "Gum.jpg"
        },
        {
            "name": "Old Shoes",
            "price": 55,
            "featured": false,
            "rating": 3.1,
            "createdAt": "1930-9-22",
            "company": "Plain Ol Corp.",
            "image": "old.jfif"
        }
    ]
}